ARMflames/Comments.py
ARMflames/FLAMES.py
ARMflames/Split.py
ARMflames/__init__.py
ARMflames/gui.py
ARMflames/static/Capture.JPG
ARMflames/static/Capture1.JPG
ARMflames/static/Capture2.JPG
ARMflames/static/Capture3.JPG
ARMflames/static/Capture4.JPG
ARMflames/static/Capture5.JPG
ARMflames/static/Capture6.JPG
ARMflames/static/GitPost.png
ARMflames/static/download.jpg
ARMflames/static/instraPost.png
ARMflames-1.0.3.dist-info/License.txt
ARMflames-1.0.3.dist-info/METADATA
ARMflames-1.0.3.dist-info/WHEEL
ARMflames-1.0.3.dist-info/entry_points.txt
ARMflames-1.0.3.dist-info/top_level.txt
ARMflames-1.0.3.dist-info/RECORD
